doc2python/__init__.py
doc2python/reader.py
doc2python-0.0.7.dist-info/METADATA
doc2python-0.0.7.dist-info/WHEEL
doc2python-0.0.7.dist-info/licenses/LICENSE
doc2python-0.0.7.dist-info/RECORD
